messaging_schema/__init__.py
messaging_schema/exchanges/__init__.py
messaging_schema/exchanges/detector.py
messaging_schema/models/__init__.py
messaging_schema/models/detect.py
messaging_schema/queues/__init__.py
messaging_schema/queues/detector.py
ai_image_detector_messaging_schema-0.3.0.dist-info/METADATA
ai_image_detector_messaging_schema-0.3.0.dist-info/WHEEL
ai_image_detector_messaging_schema-0.3.0.dist-info/RECORD
