Metadata-Version: 2.3
Name: ai-image-detector-messaging-schema
Version: 0.3.0
Summary: 
Author: ycalk
Author-email: alosev752@gmail.com
Requires-Python: >=3.11,<4.0
Classifier: Programming Language :: Python :: 3
Classifier: Programming Language :: Python :: 3.11
Classifier: Programming Language :: Python :: 3.12
Classifier: Programming Language :: Python :: 3.13
Requires-Dist: faststream[rabbit] (>=0.5.47,<0.6.0)
